ballyregan/__init__.py
ballyregan/core/exceptions.py
ballyregan/core/logger.py
ballyregan/core/utils.py
ballyregan/fetcher.py
ballyregan/filterer.py
ballyregan/models/__init__.py
ballyregan/models/hashable.py
ballyregan/models/proxy.py
ballyregan/providers/__init__.py
ballyregan/providers/free_proxy_list.py
ballyregan/providers/geonode.py
ballyregan/providers/interface.py
ballyregan/providers/proxy_list_download.py
ballyregan/providers/socks_proxy.py
ballyregan/providers/ssl_proxies.py
ballyregan/providers/us_proxy.py
ballyregan/validator.py
cli/app.py
cli/core/config.py
cli/core/utils.py
ballyregan-1.0.5.dist-info/entry_points.txt
ballyregan-1.0.5.dist-info/LICENSE
ballyregan-1.0.5.dist-info/WHEEL
ballyregan-1.0.5.dist-info/METADATA
ballyregan-1.0.5.dist-info/RECORD
