Metadata-Version: 2.1
Name: ballyregan
Version: 1.0.5
Summary: Find fetch & validate free proxies fast.
License: Apache License, Version 2.0
Keywords: python,proxy,http-proxy,https-proxy,socks-proxy,proxy-list,proxy-checker,python-proxy,proxy-fetcher,get-proxy
Author: idandaniel
Author-email: idandaniel12@gmail.com
Requires-Python: >=3.9,<4.0
Classifier: License :: Other/Proprietary License
Classifier: Programming Language :: Python :: 3
Classifier: Programming Language :: Python :: 3.10
Classifier: Programming Language :: Python :: 3.9
Requires-Dist: Faker (>=15.1.1,<16.0.0)
Requires-Dist: aiohttp (>=3.8.3,<4.0.0)
Requires-Dist: aiohttp-proxy (>=0.1.2,<0.2.0)
Requires-Dist: bs4 (>=0.0.1,<0.0.2)
Requires-Dist: click (>=8.1.3,<9.0.0)
Requires-Dist: html5lib (>=1.1,<2.0)
Requires-Dist: loguru (>=0.6.0,<0.7.0)
Requires-Dist: lxml (>=4.9.1,<5.0.0)
Requires-Dist: pandas (>=1.5.0,<2.0.0)
Requires-Dist: prettytable (>=3.4.1,<4.0.0)
Requires-Dist: pydantic (>=1.10.2,<2.0.0)
Requires-Dist: requests (>=2.28.1,<3.0.0)
Requires-Dist: typer[all] (>=0.6.1,<0.7.0)
Requires-Dist: update (>=0.0.1,<0.0.2)
